{
    "moves": {
        "1. e4 e5 2. Nf3 d6": "Philidor Defence: My 2nd philidor in this ongoing tournment",
        "3. d4": "The usual philidor stuff",
        "3... Bg4": "this B development is premature - is amply demonstrated in one of the Morphys Game but players still persist ...",
        "4. dxe5 Bxf3": "Forced, If 4....,dxe5; then 5.Qxd8 & 6.Nxe5 _ white is a healthy p up.",
        "5. Qxf3 dxe5 6. Bc4": "Develops & aims at blacks weak spot -f7p. ",
        "6... Nf6": "develops & blocks the f7#; but white shifts his Q to b-file",
        "7. Qb3": "sets a battery & reinstates the threat on f7-p & has another threat on b7-p",
        "7... Qe7": "Defends the main f7p",
        "8. Nc3": "Text is better than 8.Qxb7 as it is met with 8...,Qb4  when white is forced to Q swap. Text blocks the check, defends the e4-p & white is now ready for Qxb7 ",
        "8... b6": "Black deviates. In the historical game Morphys opponent chose ....,c6 to defend his b7-p & here ...,",
        "9. Bg5": "The famous pin ..., threat is Nd5 ",
        "9... h6": "It seems blacks has underetimated the threat or overlooked",
        "10. Nd5": "Ignors blacks attack & counters with my big one",
        "10... Qd8": "This leaves his f7-p hanging & white goes for the kill. Better for black was 10....,Qd7, though here also white wins but not as fast as in the game, as after 11.Bxf6 - wins a piece  & black cant take piece due to 12.Nxf6  - forks both Q & K",
        "11. Nxf6+": "This exchange clears the attacking diagonal ",
        "11... gxf6 12. Bxf7+ Kd7 13. Qe6#": "An excellent #"
    },
    "url": "https://gameknot.com/annotation.pl/41st-gk-tournament?gm=13163",
    "gameName": "41st GK tournament",
    "players": "smartmoves (1337) vs. vioclus (1245)",
    "opening": "Philidor's defence (C41)"
}