{
    "moves": {
        "1. e4 e5 2. Nf3 Nc6 3. Bb5": "My favorit opening",
        "3... Bc5 4. O-O Nge7 5. c3 Bb6 6. d4 exd4 7. cxd4 d5 8. exd5 Nxd5 9. Re1+ Be6 10. Bg5 Qd6 11. Nbd2 f6 12. Nc4 Qd7": "Up to now its all know theory. Now normally Qe7 is played, to avoid what is coming now.",
        "13. Nfe5": "The Knight on c6 pins the Queen, so the King side will become very vulnerable.",
        "13... fxe5 14. Nxe5 Qd6 15. Bxc6+": "Maybee the move Qf3 was better for white.",
        "15... bxc6 16. Rc1 O-O": "White is getting some material back with attack",
        "17. Rxc6 Qb4": "The Queen has no good fields anymore",
        "18. Nd3 Qxd4 19. Rcxe6": "I regain the bishop",
        "19... Qc4 20. Re6e4": "Black needs her Queen so Qb5 was better.",
        "20... Qxa2 21. Ra4 Bxf2+": "panic ?",
        "22. Nxf2 Qxb2 23. Qxd5+ Kh8 24. Nd3": "Qb6 was the better move",
        "24... Qc2 25. Bh6": "You allowed me this \"petite comnisaison\". If gxh6, then Qe5+ and mate in a couple of moves",
        "25... Qc3 26. Rd4 Rae8 27. Rxe8 Rxe8": "Now its over, Queen + Rook + Bischop against Rook ...",
        "28. Qe5": ""
    },
    "url": "https://gameknot.com/annotation.pl/67th-gk-tournament?gm=33295",
    "gameName": "67th GK tournament",
    "players": "esmet (2313) vs. hetconnection (1757)",
    "opening": "Ruy Lopez (C64), classical defence, Zaitsev variation"
}