{
    "moves": {
        "1. d4": "0.28/20 7 Ambos \u00c3\u00baltima jugada del libro\n",
        "1... d5": "0.23/19 7 \n",
        "2. c4": "0.25/20 6\n",
        "2... c6": "0.20/18 6 (e6)\n",
        "3. Nf3": "0.32/19 14 (cxd5)\n",
        "3... Nf6": "0.28/ 20 8\n",
        "4. Bf4": "0.30/19 5 (cxd5)\n",
        "4... dxc4": "0.19/19 8 (Bf5)\n",
        "5. e3": "0.35/19 7\n",
        "5... b5": "0.16/19 8 (Be6)\n",
        "6. a4": "0.26/18 3 (Be2)\n",
        "6... e6": "-0.12/17 3 (Nd5)\n",
        "7. Be2": "0.09/19 43 (Nc3)\n",
        "7... Bb4+": "-0.20/19 6 (Nd5)\n",
        "8. Nfd2": "0.19/19 7 (Nc3)\n",
        "8... O-O": "-0.44/17 3  (Nd5)\n",
        "9. O-O": "0.19/18 7\n",
        "9... Bb7": "-0.38/18 10 (Nbd7)\n",
        "10. Qc2": "-0.03/17 19\n",
        "10... Nd5": "-0.36/18 6 (Nbd7)\n",
        "11. Bg3": "0.14/16 2\n",
        "11... Nd7": "-0.46/17 9 (Be7)\n",
        "12. Nc3": "0.04/16 9 (e4)\n",
        "12... a6": "-0.43/17 4\n",
        "13. h3": "-0.15/17 14 (e4)\n",
        "13... f5": "-0.51/16 3 (Be7)\n",
        "14. Rfd1": "-0.15/17 15 (e4)\n",
        "14... Nd7f6": "-0.56/17 6 (Be7)\n",
        "15. Be5": "-0.28/16 4\n",
        "15... Qe7": "-0. 70/17 6 (Nd7)\n",
        "16. e4": "-0.18/17 6 (Rac1)\n",
        "16... Bxc3": "-0.64/19 7 (fxe4)\n",
        "17. exd5": "-0.13/16 2\n",
        "17... Bb4": "-0.68/19 3\n",
        "18. dxe6": "-0.14/17 1\n",
        "18... Nd5": "-0.64/19 4\n",
        "19. b3": "-0. 14/17 1\n",
        "19... c3": "-0.71/18 3\n",
        "20. Nf3": "-0.18/17 3 (Nf1)\n",
        "20... Qxe6": "-0.71/16 2\n",
        "21. Rde1": "-0.24/17 2 (Ne1)\n",
        "21... Rae8": "-0.80/20 7\n",
        "22. Bd3": "-0.26/18 2\n",
        "22... Qf7": "-0.78/19 20\n",
        "23. Re2": "-0.31/17 8\n",
        "23... Bc8": "-0.85/19 5\n",
        "24. Ng5": "-0.36/18 4\n",
        "24... Qd7": "-0.84/19 15 (Qh5)\n",
        "25. Nf3": "-0.54/18 12\n",
        "25... Bd6": "-0.84/19 12\n",
        "26. Rd1": "-0.65/17 4\n",
        "26... Ba3": "-0.89/19 4  (Bxe5)\n",
        "27. Rb1": "-0.57/17 3 (Qa2)\n",
        "27... Re7": "-0.97/18 2 (Be7)\n",
        "28. Ree1": "-0.63/17 8 (Rd1)\n",
        "28... Rfe8": "-1.15/15 2\n",
        "29. Bf1": "-0.68/16 2 (Rf1)\n",
        "29... g6": "-1.17/15 1 (Bd6)\n",
        "30. h4": "-0.57/16 2 (Kh2)\n",
        "30... f4": "-0.75/17 12 (Bd6)\n",
        "31. b4": "-0.62/16 2\n",
        "31... Bxb4": "-0.86/ 17 3\n",
        "32. axb5": "-0.47/16 2 (Rxb4)\n",
        "32... axb5": "-0.66/18 3\n",
        "33. Rxb4": "-0.45/17 2\n",
        "33... Nxb4": "-0.68/17 1\n",
        "34. Qxc3": "-0.41/16 0\n",
        "34... Nd5": "-0.75/18 2\n",
        "35. Qc2": "-0.38/18 2\n",
        "35... b4": "-0.48/17 6 (Bb7)\n",
        "36. Bd3": "-0.23/16 2\n",
        "36... Qg4": "-0.37/17 2\n",
        "37. Qc5": "-0.19/17 1\n",
        "37... h6": "-0.51/18 4\n",
        "38. Qxc6": "-0.15/17 1\n",
        "38... Bb7": "-0.41/18 1\n",
        "39. Qxg6+": "-0.15/15 0\n",
        "39... Qxg6": "-0.49/18 1\n",
        "40. Bxg6": "-0.11/15 0\n",
        "40... Ra8": "-0.48/20 2\n",
        "41. Rb1": "-0.21/18 2\n",
        "41... Re6": "-0.45/20 3 (Bc6)\n",
        "42. Bd3": "-0.14/17 2\n",
        "42... Rb6": "-0.45/17 1\n",
        "43. Bc4": "-0.12/19 4\n",
        "43... Rc8": "-0.51/17 1 (Kf8)\n",
        "44. Nd2": "-0.12/18 1\n",
        "44... Kf8": "-0.48/17 2\n",
        "45. f3": "-0.17/18 1 \n",
        "45... h5": "-0.47/20 3\n",
        "46. Kf2": "-0.28/18 3\n",
        "46... Ne3": "-0.49/18 1 (Nc3)\n",
        "47. Bd3": "-0.20/ 17 1\n",
        "47... Rc3": "-0.54/19 3\n",
        "48. Bh7": "-0.29/17 1\n",
        "48... Nd5": "-0.58/20 3\n",
        "49. Nb3": "-0.34/18 6\n",
        "49... Ke7": "-0.51/18 3 (Ra6)\n",
        "50. Nc5": "-0.18/17 1 (Kg1)\n",
        "50... Ra3": "-0.75/16 1 (Bc6)\n",
        "51. Nxb7": "-0.36/16 1\n",
        "51... Rxb7": "-0.94/19 2\n",
        "52. Be4": "-1.21/17 3 (Bg8)\n",
        "52... Nc3": "-1.24/16 2 (Ra2+)\n",
        "53. Bxb7": "-1.76/18 4\n",
        "53... Nxb1": "-1.31/17 1\n",
        "54. Bxf4": "-1.71/16 1\n",
        "54... b3": "-1. 50/16 3\n",
        "55. Bg5+": "-1.72/17 1 (Bd5)\n",
        "55... Ke6": "-1.36/17 1 (Kd7)\n",
        "56. g4": "-2.28/15 2\n",
        "56... hxg4": "-1.48/17 3\n",
        "57. Bc8+": "-2.33/16 1 (d5+)\n",
        "57... Kd5": "-1.54/17 1\n",
        "58. Bxg4": "-2.68/ 16 1\n",
        "58... Nc3": "-1.65/18 2 (b2)\n",
        "59. Bf5": "-3.30/18 5\n",
        "59... Kc4": "-1.75/18 5 (b2)\n",
        "60. d5": "-2.87/16 1\n",
        "60... Ra5": "-1.83/19 1\n",
        "61. Bg6": "-3.08/18 1\n",
        "61... Rxd5": "-1.86/19 2\n",
        "62. Be7": "-3.37/17 0\n",
        "62... Ra5": "-1.89/19 2 (b2)\n",
        "63. Kg3": "-3.68/17 2 (Bf7+)\n",
        "63... b2": "-1.98/16 1\n",
        "64. Bc2": "-4.07/19 2 (Kf2)\n",
        "64... Ne2+": "-2.12/17 2 (Nd5)\n",
        "65. Kg4": "-4.05/17 1\n",
        "65... Ra6": "-2.36/18 3 (Nd4)\n",
        "66. Bg5": "-4.03/17 1 (Bf8)\n",
        "66... Nd4": "-2.69/16 0\n",
        "67. Bb1": "-4.31/ 16 0\n",
        "67... Ra1": "-2.78/17 0\n",
        "68. Bh7": "-4.47/16 0\n",
        "68... Rg1+": "-3.50/18 3\n",
        "69. Kh5": "-4.49/ 18 0 (Kf4)\n",
        "69... Kc3": "-3.86/15 1 (Nxf3)\n",
        "70. f4": "-8.77/16 3 (Bd8)\n",
        "70... Rd1": "-4.62/17 2\n",
        "71. Bf6": "-8.43/14 1 (Bd8)\n",
        "71... Rd3": "-6.45/16 2\n",
        "72. Bxd4+": "-10.34/16 1 (Bg6)\n",
        "72... Kxd4": "-10.84/16 0\n"
    },
    "url": "https://gameknot.com/annotation.pl/blitz-5m?gm=56232",
    "gameName": "Blitz 5m",
    "players": "Houdini 4 Pro x64  vs. Komodo 8 64-bit ",
    "opening": "QGD Slav (D11), Breyer variation"
}