{
    "moves": {
        "1. d4": "not much to say but enjoyable game for me at least, please send me your comments.",
        "1... d5 2. e3 Nf6 3. Be2 Bf5 4. Nf3 e6 5. Nh4 Nbd7 6. Nxf5 exf5 7. O-O Bd6 8. Qd3 a6 9. Qxf5": "here she comes!",
        "9... Ne4 10. Qxd5 Qe7 11. f3 Ng3 12. hxg3 Bxg3 13. Qxb7 O-O 14. Qe4 Qd6 15. f4 Qh6 16. Bh5 Qxh5 17. Rf2 Qh2+ 18. Kf1 Qh1+ 19. Ke2 Bxf2": "bye bishop...",
        "20. Bd2 Qh4": "had to save my bishop i gave up :)",
        "21. Qf5 Nf6 22. Qh3 Rfe8 23. Nc3 Qxh3 24. gxh3 Bh4 25. Rg1 Nh5 26. Kf3 f5": "now we dance..",
        "27. Nd5 Ra7 28. Ba5 Rb8 29. b3 Rb5 30. Nb4 c5 31. c4 Rxb4 32. Bxb4 cxb4 33. d5 Nf6 34. d6 Ne4 35. Rd1 Rd7 36. Rd5 g6 37. c5 Kf7 38. c6": "perhaps the turning point of the game?",
        "38... Rxd6 39. c7 Rc6": "a blunder here by either of us, will come at the cost of the game",
        "40. Rd7+ Ke6 41. Rxh7 Bf6 42. Rh6 Rxc7 43. Rxg6 Rc2 44. h4": "i did not see it, do you????",
        "44... Rxa2": "not yet?",
        "45. h5": "i guess not, but now i do!!",
        "45... Rf2#": ""
    },
    "url": "https://gameknot.com/annotation.pl/challenge-from-ishamael13?gm=7291",
    "gameName": "Challenge from ishamael13",
    "players": "ishamael13 (1575) vs. beresford13861 (1345)",
    "opening": "Queen's pawn (D00), stonewall attack"
}