{
    "moves": {
        "1. c4 Nf6 2. Nc3 e6 3. e4": "To prevent Black's d5 push.",
        "3... Bb4": "This leaves the center to White forces.",
        "4. e5": "! To gain both space and tempo.",
        "4... Bxc3 5. bxc3 Ne4 6. Qg4": "! Double threat in e4 and g7.",
        "6... Ng5": "A mistake. 6. Nc5 was necessary.",
        "7. h4": "The knight is lost.",
        "7... h5 8. hxg5": "Black resigns."
    },
    "url": "https://gameknot.com/annotation.pl/english-mikenas-carls-variation-2-e6-3-e4?gm=12558",
    "gameName": "English, Mikenas-Carls variation (2. ... e6 3. e4)",
    "players": "pim1 (1556) vs. yshulzin (1511)",
    "opening": "English (A18), Mikenas-Carls variation"
}