{
    "moves": {
        "1. e4 e5 2. Nf3 Nc6 3. Bc4": "the signature move...",
        "3... Nf6": "considered weak: Bc5, and then Nf6...",
        "4. Ng5": "here is why: f7 is under pressure...",
        "4... d5": "the only move...",
        "5. exd5 Nxd5": "not the best: best is Na5, Bb5+, c6, dxc6, bxc6, Qf3!...",
        "6. Nxf7": "the Fegatello attack: Fischer called this the Fried Liver attack...",
        "6... Kxf7 7. Qf3+ Ke6": "hard to believe: but this is the best reply...",
        "8. Nc3": "persisting...",
        "8... Ncb4": "a pity: best was Nce7: Black is trying to capitalize on pawn c2...",
        "9. O-O Qf6": "a very bad idea...",
        "10. Bxd5+ Nxd5 11. Qxd5+": "Black resigned..."
    },
    "url": "https://gameknot.com/annotation.pl/fiercequeen-handling-the-italian?gm=65426",
    "gameName": "fiercequeen, handling the Italian...",
    "players": "fiercequeen (2059) vs. shetpigo (1765)",
    "opening": "two knights defence (C57), Fegatello attack, Leonhardt variation"
}