{
    "moves": {
        "1. c4": "I'm playing black here and i haven't noticed how high his grade is yet.",
        "1... e5 2. Nc3 Nf6 3. Nf3 d6": "Fairly normal opening up to here so i don't feel too bad yet.",
        "4. Qc2 Nc6 5. e3 Bg4": "Not much point because he would just defend with bishop. I'm the kind of guy who doesn't want to make the first moves. I like to counter attack and not start it.",
        "6. Be2": "As expected",
        "6... Qd7": "Just wasting moves. I know I know. for all you 'GREAT' chess players out there, it's not a wise thing to do. But oh well.",
        "7. d4": "At last the first proper attack.",
        "7... exd4 8. exd4 Bxf3 9. Bxf3 Nxd4": "After that exchange i am a pawn up!!!",
        "10. Qd3 Nxf3+ 11. Qxf3": "Oh yeah, i also like killing pieces.",
        "11... Rb8": "Trying to defend pawn",
        "12. O-O Be7": "I wanna castle now.",
        "13. Re1 O-O 14. Bg5": "Go away",
        "14... h6": "Meh",
        "15. Bh4 Rfe8 16. Re3": "I'm not sure what that was supposed to do. If you have ideas leave a comment!!!",
        "16... Qg4": "I want to trade queens, please?",
        "17. Qxg4 Nxg4": "Thanks",
        "18. Rxe7": "Damn",
        "18... Rxe7 19. Bxe7 f6": "HAHAHAHAHA no escape for you now!!!!",
        "20. Re1": "Desperate attempt to save it.",
        "20... Re8": "DIE BISHOP!!!",
        "21. Nd5 Kf7": "HEH HEH HEH ",
        "22. f4": "I guess that was supposed to stop my knight moving anywhere. But that won't stop me!!!",
        "22... c6": "DIE KNIGHT",
        "23. Bxd6": "Didn't see that",
        "23... Rxe1#": "But i'm sure he didn't see THAT. HAHAHAHA"
    },
    "url": "https://gameknot.com/annotation.pl/chess-game?gm=48646",
    "gameName": "Chess game",
    "players": "ajvs (1854) vs. hselikin (1383)",
    "opening": "English (A22), Bellon gambit"
}