{
    "moves": {
        "1. e4": " this is goldmedal20. my old account is gone because my email got hacked and my computer died on me. I might be rusty since have not played munch chess since the computer started acting up.  I am black and tom is white",
        "1... e5": "king pawn opening.",
        "2. Nc3": " next couple of moves we both was building minor pieces .",
        "2... Nc6": " building up my knights",
        "3. Nd5": "leading the way with his knight. one thing someone told me not to move minor pieces past your pawn eraly in the game. am I right?",
        "3... Bc5": "building up my bishop",
        "4. d3": "trying to gain control of the middle",
        "4... Nh6": " bad move on my part. you should never pat the knight to the end row",
        "5. Nf3": " has both knights out",
        "5... O-O": "castle king side",
        "6. Bxh6": "lost knight. must be out of myself since i have not played for a while.",
        "6... gxh6": "took minor piece",
        "7. c3": "moves pawns",
        "7... Kh8": " moves king to safe spot. no double pawning ",
        "8. d4": "what is it called when a piece could have a choose on taking 2 pieces?",
        "8... Bb6": " I knew i could only save one piece",
        "9. dxe5": "double pawning",
        "9... d6": "tradeoff in pawns",
        "10. exd6": "takes pawn",
        "10... cxd6": "takes pawn",
        "11. Nxb6": "attacking with his knight",
        "11... Rb8": "moves my rook to a safe spot",
        "12. Nxc8": "takes bishop",
        "12... Qxc8": "takes knight",
        "13. Qxd6": "attacking with queen",
        "13... Ra8": "moves rook to safe spot",
        "14. Bb5": "putting on the heat",
        "14... a6": " moves pawn",
        "15. Bxc6": "lost all minor pieces",
        "15... bxc6": "takes bishop",
        "16. Qxh6": "takes pawn",
        "16... Rb8": "gets ready to move my major pieces out",
        "17. Ng5": "i am going loose soon",
        "17... Rxb2": " got of get pieces out fast",
        "18. Rd1": "moves rook",
        "18... Rxa2": "bad move",
        "19. Qxh7#": "check mate"
    },
    "url": "https://gameknot.com/annotation.pl/lets-play-chess?gm=48636",
    "gameName": "Let's play chess",
    "players": "tom2751 (1156) vs. reachforgold (1200)",
    "opening": "Vienna game, Max Lange defence (C25)"
}