{
    "moves": {
        "1. e4": "chocs away ginger.....",
        "1... c5": "roger wilko...popular reply",
        "2. Nf3": "welcome aboard neddy",
        "2... Nc6": "meet (one of) your doppelgangers",
        "3. Bc4": "brucey bishop comes out to cover d5",
        "3... e6": "not the reply I expected...",
        "4. Nc3": "neddy 2 comes out to help with the middle-board scrap",
        "4... a6": "the bounder blocks my bishop from attacking his neddy",
        "5. O-O": "I like to castle, gives the king that warm feeling...either that or it's time for a new adult nappy :oO",
        "5... b5": "hmm my bishop is being pressured by black's pesky pawns \r\n",
        "6. Be2": "ok ~ tucks bishop away out of trouble, but losing ground in the middle board in doing so :o/",
        "6... Bb7": "as expected...",
        "7. b3": "i'll have some of that !",
        "7... Nge7": "ok a different way of bringing ned#4 out, the gee-gee's are strong though -protecting each other",
        "8. Bb2": "as expected",
        "8... d5": "black makes his play for the centre board....fire at will",
        "9. exd5": "mutty accepts the exchange",
        "9... Nxd5": "ned#4 comes out to hassle neddy1",
        "10. Nxd5": "chomp !",
        "10... exd5": "...back at ya-- greedy pawn",
        "11. Re1": "squares up on e file",
        "11... Be7": "nice, bishop has protected King, and is lined up with his queen too",
        "12. Bxg7": "yum....g7 prawns sure are tasty ma",
        "12... Rg8": "ohh...ok reverse.......",
        "13. Be5": "back to the centre then",
        "13... Qd7": "hmm queen wants to get on my King..hmm need to be decisive here",
        "14. Bg3": "ok bishop come back here young man - there's pots to wash",
        "14... O-O-O": "black castles to queen's side....a tad unusual",
        "15. Nd4": "you oaf - what are you doing ? ...get a grip muttit",
        "15... Nxd4": "a gift for black thanks to muttit's muppetry *slap*",
        "16. Bd3": "time to re-group muttit, get some material back if at all possible",
        "16... h6": "ok i thought he might go Rh8  but there you go...",
        "17. c3": "ok move the troops out, get neddy get neddy",
        "17... Ne6": "back she goes...bkrrrrppppp ",
        "18. Qh5": "queen comes out to try for a tasty prawn on h6",
        "18... Bg5": "ohh - a bishop & a pawn locked together...every opponents nightmare :o<",
        "19. Re2": "lets see what these rook chappies can do, building pressure on e file",
        "19... d4": "i'm feeling a little squashed now...... 'get orf my land' ",
        "20. c4": "not brilliant but i don't want to unleash that tasty queen / rook combo on the d file",
        "20... bxc4": "< chomp >",
        "21. bxc4": "...touche !!!",
        "21... Bf4": "hmm my king is getting a little scared...",
        "22. Bf5": "ok lets try & halt this nonsense...the black gee gee is going nowhere fast, and his queen is clumsily sat in line of his king \r\n\r\n- hands up if you've been punished for doing that in the past :o/",
        "22... Bxg3": "bish bash bosh...",
        "23. fxg3": "ok that pawn will do ~ a nice little threesome is now going on next to muttit's king, looks messy but can be effective",
        "23... Rgh8": "oi I wanted to eat that h6 pawn !\r\n\r\nblack does rh8 to save his sorry rear-end",
        "24. Re5": "hmm now if I can just connect my queen & rook...  ;o)",
        "24... Qc6": "oops !!! :o)\r\n\r\ni'll have some of neddy i think ....muuuhhhhaaawwwoooaaaarrr",
        "25. Bxe6+": "The decisive move, black exchanges & takes white bishop with pawn, in the mean time whites rook & queen have connected \r\n\r\nEureka ka ka ka ka ",
        "25... fxe6": "black has to take back",
        "26. Rxc5": "that's the boy, I will be lunching on queen - she is sunk",
        "26... Rde8": "protects pawn ...well they all count",
        "27. Rxc6+": "yum :OD",
        "27... Bxc6": "with the material advantage in muttit's court at last...black is in deep doo doo",
        "28. Qc5": "muttit fancies a bit of bishop for pud....and black resigns.\r\n\r\nThankyou for watching, please put all your rubbish in the bins on your way out.  :o)"
    },
    "url": "https://gameknot.com/annotation.pl/lets-play-chess?gm=11702",
    "gameName": "Let's play chess",
    "players": "muttit (1599) vs. gggk (1635)",
    "opening": "Sicilian defence (B30)"
}