{
    "moves": {
        "1. e3": " is this still a king oeping",
        "1... e5": "opening  I am black",
        "2. Qf3": "queen   queen  is good to the queen going this  soon",
        "2... Nf6": "knight",
        "3. Qf5": "queen",
        "3... g6": "pawn",
        "4. Qxe5+": "check",
        "4... Be7": "safe",
        "5. d4": "pawn",
        "5... d6": "pawn",
        "6. Qb5+": "likes to move that queen",
        "6... c6": "pawn",
        "7. Qc4": "back",
        "7... Be6": "bishop",
        "8. Qb4": "queen",
        "8... a5": "pawn this is one weird game",
        "9. Qa4": "queen",
        "9... b5": "pawn",
        "10. Qa3": "queen",
        "10... c5": "pawn",
        "11. Bxb5+": "check",
        "11... Bd7": "bishop",
        "12. Qa4": " is this a trap",
        "12... Nc6": "blocks",
        "13. Bxc6": "bishop",
        "13... Bxc6": "bishop",
        "14. Qxc6+": "check",
        "14... Nd7": "knight",
        "15. Qb7": "queen",
        "15... a4": "[awen",
        "16. b3": "pawn",
        "16... axb3": "pawn",
        "17. Nc3": "knight",
        "17... bxc2": "pawn  white times out i win"
    },
    "url": "https://gameknot.com/annotation.pl/r-lets-play-chess?gm=66109",
    "gameName": "[R] Let's play chess",
    "players": "kingmopar (671) vs. goldmedal10 (681)",
    "opening": "Amsterdam attack (A00)"
}